ffmpegio_plugin_mpl/__init__.py
ffmpegio_plugin_mpl-0.1.1.dist-info/LICENSE
ffmpegio_plugin_mpl-0.1.1.dist-info/METADATA
ffmpegio_plugin_mpl-0.1.1.dist-info/WHEEL
ffmpegio_plugin_mpl-0.1.1.dist-info/entry_points.txt
ffmpegio_plugin_mpl-0.1.1.dist-info/top_level.txt
ffmpegio_plugin_mpl-0.1.1.dist-info/RECORD
