Metadata-Version: 2.1
Name: ffmpegio-plugin-mpl
Version: 0.1.1
Summary: ffmpegio plugin to create videos from matploglib Figures
Home-page: https://python-ffmpegio.github.io/python-ffmpegio
License: GPL-2.0 License
Project-URL: Repository, https://github.com/python-ffmpegio/python-ffmpegio
Project-URL: Discussions, https://github.com/python-ffmpegio/python-ffmpegio/discussions
Project-URL: Issues, https://github.com/python-ffmpegio/python-ffmpegio/issues
Project-URL: Pull Requests, https://github.com/python-ffmpegio/python-ffmpegio/pulls
Keywords: multimedia,ffmpeg,matplotlib
Classifier: Development Status :: 4 - Beta
Classifier: License :: OSI Approved :: GNU General Public License v2 (GPLv2)
Classifier: Topic :: Multimedia :: Video
Classifier: Topic :: Multimedia :: Video :: Conversion
Classifier: Programming Language :: Python :: 3.7
Classifier: Programming Language :: Python :: 3.8
Classifier: Programming Language :: Python :: 3.9
Classifier: Programming Language :: Python :: 3.10
Requires-Python: >=3.7
License-File: LICENSE
Requires-Dist: ffmpegio-core (>=0.3)
